new_component/__init__.py
new_component/_config.py
new_component/_confirms.py
new_component/_constants.py
new_component/_echos.py
new_component/_jinja.py
new_component/_utils.py
new_component/_version.py
new_component/cli.py
new_component/main.py
new_component/py.typed
new_component/templates/component.js.j2
new_component/templates/index.js.j2
new_component/VERSION
new_component-0.6.0.dist-info/entry_points.txt
new_component-0.6.0.dist-info/WHEEL
new_component-0.6.0.dist-info/METADATA
new_component-0.6.0.dist-info/licenses/LICENSE
new_component-0.6.0.dist-info/RECORD
