Metadata-Version: 2.1
Name: new_component
Version: 0.6.0
Summary: Quickly create opinionated Styled Components for React Projects
License: MIT
Keywords: script,javascript,styled-components
Author-email: Ian Cleary <github@iancleary.me>
Requires-Python: >=3.11
Classifier: Programming Language :: Python :: 3.11
Classifier: Topic :: Software Development :: Code Generators
Requires-Dist: Jinja2==3.1.2
Requires-Dist: colorama==0.4.6
Requires-Dist: rich==13.3.5
Requires-Dist: shellingham==1.5.0.post1
Requires-Dist: typer==0.9.0
Project-URL: Documentation, https://new-component.iancleary.me
Project-URL: Homepage, https://new-component.iancleary.me
Project-URL: Repository, https://github.com/iancleary/new-component
